{
  "primaryNavLinksHome": [
    {
      "name": "Resume drive link",
      "href": "{{RESUME_LINK}}",
      "text": "Resume PDF"
    },
    {
      "name": "Project Showcase Page Link",
      "href": "{{PROJECTS_SHOWCASE_PAGE_LINK}}",
      "text": "Projects Showcase"
    },
    {
      "name": "Web Linktree Page Link",
      "href": "{{LINKTREE_SHOWCASE_PAGE_LINK}}",
      "text": "Web Linktree"
    },
    {
      "name": "Resume Showcase Page Link",
      "href": "{{RESUME_SHOWCASE_PAGE_LINK}}",
      "text": "Resume Showcase"
    },
    {
      "name": "Blog Showcase Page Link",
      "href": "{{BLOG_SHOWCASE_PAGE_LINK}}",
      "text": "Blog Showcase"
    }
  ],
  "primaryNavLinksPS": [
    {
      "name": "Resume drive link",
      "href": "{{RESUME_LINK}}",
      "text": "Resume PDF"
    },
    {
      "name": "Home Page Link",
      "href": "{{HOME_PAGE_LINK}}",
      "text": "Home Page"
    },
    {
      "name": "Web Linktree Page Link",
      "href": "{{LINKTREE_SHOWCASE_PAGE_LINK}}",
      "text": "Web Linktree"
    },
    {
      "name": "Resume Showcase Page Link",
      "href": "{{RESUME_SHOWCASE_PAGE_LINK}}",
      "text": "Resume Showcase"
    },
    {
      "name": "Blog Showcase Page Link",
      "href": "{{BLOG_SHOWCASE_PAGE_LINK}}",
      "text": "Blog Showcase"
    }
  ],
  "primaryNavLinksWLT": [
    {
      "name": "Resume drive link",
      "href": "{{RESUME_LINK}}",
      "text": "Resume PDF"
    },
    {
      "name": "Home Page Link",
      "href": "{{HOME_PAGE_LINK}}",
      "text": "Home Page"
    },
    {
      "name": "Project Showcase Page Link",
      "href": "{{PROJECTS_SHOWCASE_PAGE_LINK}}",
      "text": "Projects Showcase"
    },
    {
      "name": "Resume Showcase Page Link",
      "href": "{{RESUME_SHOWCASE_PAGE_LINK}}",
      "text": "Resume Showcase"
    },
    {
      "name": "Blog Showcase Page Link",
      "href": "{{BLOG_SHOWCASE_PAGE_LINK}}",
      "text": "Blog Showcase"
    }
  ],
  "primaryNavLinksRS": [
    {
      "name": "Resume drive link",
      "href": "{{RESUME_LINK}}",
      "text": "Resume PDF"
    },
    {
      "name": "Home Page Link",
      "href": "{{HOME_PAGE_LINK}}",
      "text": "Home Page"
    },
    {
      "name": "Project Showcase Page Link",
      "href": "{{PROJECTS_SHOWCASE_PAGE_LINK}}",
      "text": "Projects Showcase"
    },
    {
      "name": "Web Linktree Page Link",
      "href": "{{LINKTREE_SHOWCASE_PAGE_LINK}}",
      "text": "Web Linktree"
    },
    {
      "name": "Blog Showcase Page Link",
      "href": "{{BLOG_SHOWCASE_PAGE_LINK}}",
      "text": "Blog Showcase"
    }
  ],
  "primaryNavLinksBS": [
    {
      "name": "Resume drive link",
      "href": "{{RESUME_LINK}}",
      "text": "Resume PDF"
    },
    {
      "name": "Home Page Link",
      "href": "{{HOME_PAGE_LINK}}",
      "text": "Home Page"
    },
    {
      "name": "Project Showcase Page Link",
      "href": "{{PROJECTS_SHOWCASE_PAGE_LINK}}",
      "text": "Projects Showcase"
    },
    {
      "name": "Web Linktree Page Link",
      "href": "{{LINKTREE_SHOWCASE_PAGE_LINK}}",
      "text": "Web Linktree"
    },
    {
      "name": "Resume Showcase Page Link",
      "href": "{{RESUME_SHOWCASE_PAGE_LINK}}",
      "text": "Resume Showcase"
    }
  ]
}
